eikon/Profile.py
eikon/__init__.py
eikon/data_grid.py
eikon/eikonError.py
eikon/json_requests.py
eikon/news_request.py
eikon/symbology.py
eikon/time_series.py
eikon/tools.py
eikon/streaming_session/__init__.py
eikon/streaming_session/cache.py
eikon/streaming_session/desktop_session.py
eikon/streaming_session/istream_callback.py
eikon/streaming_session/itemstream.py
eikon/streaming_session/session.py
eikon/streaming_session/stream.py
eikon/streaming_session/stream_connection.py
eikon/streaming_session/streaming_connection_config.py
eikon/streaming_session/streamingprice.py
eikon/streaming_session/streamingprice_callback.py
eikon/streaming_session/streamingprices.py
eikon/vendor/__init__.py
eikon/vendor/requests_async/__init__.py
eikon/vendor/requests_async/adapters.py
eikon/vendor/requests_async/api.py
eikon/vendor/requests_async/asgi.py
eikon/vendor/requests_async/cookies.py
eikon/vendor/requests_async/exceptions.py
eikon/vendor/requests_async/models.py
eikon/vendor/requests_async/sessions.py
eikon/vendor/requests_async/status_codes.py
eikon/vendor/requests_async/http3/__init__.py
eikon/vendor/requests_async/http3/__version__.py
eikon/vendor/requests_async/http3/api.py
eikon/vendor/requests_async/http3/auth.py
eikon/vendor/requests_async/http3/client.py
eikon/vendor/requests_async/http3/concurrency.py
eikon/vendor/requests_async/http3/config.py
eikon/vendor/requests_async/http3/decoders.py
eikon/vendor/requests_async/http3/exceptions.py
eikon/vendor/requests_async/http3/interfaces.py
eikon/vendor/requests_async/http3/models.py
eikon/vendor/requests_async/http3/multipart.py
eikon/vendor/requests_async/http3/status_codes.py
eikon/vendor/requests_async/http3/utils.py
eikon/vendor/requests_async/http3/dispatch/__init__.py
eikon/vendor/requests_async/http3/dispatch/asgi.py
eikon/vendor/requests_async/http3/dispatch/connection.py
eikon/vendor/requests_async/http3/dispatch/connection_pool.py
eikon/vendor/requests_async/http3/dispatch/http11.py
eikon-1.1.18.dist-info/LICENSE.md
eikon-1.1.18.dist-info/METADATA
eikon-1.1.18.dist-info/WHEEL
eikon-1.1.18.dist-info/top_level.txt
eikon-1.1.18.dist-info/RECORD
