Metadata-Version: 2.1
Name: eikon
Version: 1.1.18
Summary: Python package for retrieving Eikon data.
Home-page: https://developers.refinitiv.com/eikon-apis/eikon-data-api
Author: REFINITIV
Author-email: 
License: Apache 2.0
License-File: LICENSE.md
Requires-Dist: httpx>=0.18.0
Requires-Dist: nest_asyncio>=1.5.1
Requires-Dist: datetime
Requires-Dist: pandas>=1.0.0
Requires-Dist: numpy>=1.11.0
Requires-Dist: appdirs>=1.4.3
Requires-Dist: python-dateutil
Requires-Dist: websocket-client!=1.0.0,>=0.54.0
Requires-Dist: deprecation
Requires-Dist: certifi
Requires-Dist: chardet==3.*
Requires-Dist: h2==4.*
Requires-Dist: idna==2.*
Requires-Dist: rfc3986==1.*
Requires-Dist: requests==2.*
